[
{"name": "The 5 Love Languages: The Secret to Love that Lasts", "author": "Gary Chapman"},
{"name": "The Life-Changing Magic of Tidying Up: The Japanese Art of Decluttering and Organizing", "author": "(345 used &amp new offers)"},
{"name": "Portraits of Courage: A Commander in Chief's Tribute to America's Warriors", "author": "George W. Bush"},
{"name": "The Most Beautiful: My Life with Prince", "author": "Mayte Garcia"},
{"name": "Hamilton: The Revolution", "author": "Lin-Manuel Miranda"},
{"name": "Born a Crime: Stories from a South African Childhood", "author": "Trevor Noah"},
{"name": "The Bob's Burgers Burger Book: Real Recipes for Joke Burgers", "author": "Bob's Burgers"},
{"name": "Creative Lettering and Beyond: Inspiring tips, techniques, and ideas for hand lettering your way to beautiful...", "author": "Laura Lavender"},
{"name": "The Legend of Zelda: Art & Artifacts", "author": "Nintendo"},
{"name": "The Enigma of the Owl: An Illustrated Natural History", "author": "(9 used &amp new offers)"},
{"name": "Ballerina Body: Dancing and Eating Your Way to a Leaner, Stronger, and More Graceful You", "author": "Misty Copeland"},
{"name": "The Moth Presents All These Wonders: True Stories About Facing the Unknown", "author": "Catherine Burns"}
]